[
    {
        "Time": 70929,
        "Command": "GoroutineStart",
        "Id": 1,
        "ParentId": 0,
        "From": "",
        "To": "",
        "Channel": "",
        "Value": null,
        "EventID": "",
        "Duration": 0
    },
    {
        "Time": 15017306,
        "Command": "GoroutineStart",
        "Id": 20,
        "ParentId": 1,
        "From": "",
        "To": "",
        "Channel": "",
        "Value": null,
        "EventID": "",
        "Duration": 0
    },
    {
        "Time": 15051907,
        "Command": "GoroutineStart",
        "Id": 21,
        "ParentId": 1,
        "From": "",
        "To": "",
        "Channel": "",
        "Value": null,
        "EventID": "",
        "Duration": 0
    },
    {
        "Time": 35959902,
        "Command": "GoroutineSend",
        "Id": 1,
        "ParentId": 0,
        "From": "",
        "To": "",
        "Channel": "SOgVOX52EN",
        "Value": "0",
        "EventID": "",
        "Duration": 0
    },
    {
        "Time": 35982770,
        "Command": "GoroutineReceive",
        "Id": 20,
        "ParentId": 0,
        "From": "",
        "To": "",
        "Channel": "SOgVOX52EN",
        "Value": "0",
        "EventID": "",
        "Duration": 0
    },
    {
        "Time": 117301372,
        "Command": "GoroutineSend",
        "Id": 20,
        "ParentId": 0,
        "From": "",
        "To": "",
        "Channel": "SOgVOX52EN",
        "Value": "1",
        "EventID": "",
        "Duration": 0
    },
    {
        "Time": 117318352,
        "Command": "GoroutineReceive",
        "Id": 21,
        "ParentId": 0,
        "From": "",
        "To": "",
        "Channel": "SOgVOX52EN",
        "Value": "1",
        "EventID": "",
        "Duration": 0
    },
    {
        "Time": 204384524,
        "Command": "GoroutineSend",
        "Id": 21,
        "ParentId": 0,
        "From": "",
        "To": "",
        "Channel": "SOgVOX52EN",
        "Value": "2",
        "EventID": "",
        "Duration": 0
    },
    {
        "Time": 204413301,
        "Command": "GoroutineReceive",
        "Id": 20,
        "ParentId": 0,
        "From": "",
        "To": "",
        "Channel": "SOgVOX52EN",
        "Value": "2",
        "EventID": "",
        "Duration": 0
    },
    {
        "Time": 301877387,
        "Command": "GoroutineSend",
        "Id": 20,
        "ParentId": 0,
        "From": "",
        "To": "",
        "Channel": "SOgVOX52EN",
        "Value": "3",
        "EventID": "",
        "Duration": 0
    },
    {
        "Time": 301914761,
        "Command": "GoroutineReceive",
        "Id": 21,
        "ParentId": 0,
        "From": "",
        "To": "",
        "Channel": "SOgVOX52EN",
        "Value": "3",
        "EventID": "",
        "Duration": 0
    },
    {
        "Time": 361479694,
        "Command": "GoroutineSend",
        "Id": 21,
        "ParentId": 0,
        "From": "",
        "To": "",
        "Channel": "SOgVOX52EN",
        "Value": "4",
        "EventID": "",
        "Duration": 0
    },
    {
        "Time": 361519073,
        "Command": "GoroutineReceive",
        "Id": 20,
        "ParentId": 0,
        "From": "",
        "To": "",
        "Channel": "SOgVOX52EN",
        "Value": "4",
        "EventID": "",
        "Duration": 0
    },
    {
        "Time": 442892606,
        "Command": "GoroutineSend",
        "Id": 20,
        "ParentId": 0,
        "From": "",
        "To": "",
        "Channel": "SOgVOX52EN",
        "Value": "5",
        "EventID": "",
        "Duration": 0
    },
    {
        "Time": 442934054,
        "Command": "GoroutineReceive",
        "Id": 21,
        "ParentId": 0,
        "From": "",
        "To": "",
        "Channel": "SOgVOX52EN",
        "Value": "5",
        "EventID": "",
        "Duration": 0
    },
    {
        "Time": 510934356,
        "Command": "GoroutineSend",
        "Id": 21,
        "ParentId": 0,
        "From": "",
        "To": "",
        "Channel": "SOgVOX52EN",
        "Value": "6",
        "EventID": "",
        "Duration": 0
    },
    {
        "Time": 510975208,
        "Command": "GoroutineReceive",
        "Id": 20,
        "ParentId": 0,
        "From": "",
        "To": "",
        "Channel": "SOgVOX52EN",
        "Value": "6",
        "EventID": "",
        "Duration": 0
    },
    {
        "Time": 586210065,
        "Command": "GoroutineSend",
        "Id": 20,
        "ParentId": 0,
        "From": "",
        "To": "",
        "Channel": "SOgVOX52EN",
        "Value": "7",
        "EventID": "",
        "Duration": 0
    },
    {
        "Time": 586221755,
        "Command": "GoroutineReceive",
        "Id": 21,
        "ParentId": 0,
        "From": "",
        "To": "",
        "Channel": "SOgVOX52EN",
        "Value": "7",
        "EventID": "",
        "Duration": 0
    },
    {
        "Time": 676644556,
        "Command": "GoroutineSend",
        "Id": 21,
        "ParentId": 0,
        "From": "",
        "To": "",
        "Channel": "SOgVOX52EN",
        "Value": "8",
        "EventID": "",
        "Duration": 0
    },
    {
        "Time": 676667510,
        "Command": "GoroutineReceive",
        "Id": 20,
        "ParentId": 0,
        "From": "",
        "To": "",
        "Channel": "SOgVOX52EN",
        "Value": "8",
        "EventID": "",
        "Duration": 0
    },
    {
        "Time": 732793705,
        "Command": "GoroutineSend",
        "Id": 20,
        "ParentId": 0,
        "From": "",
        "To": "",
        "Channel": "SOgVOX52EN",
        "Value": "9",
        "EventID": "",
        "Duration": 0
    },
    {
        "Time": 732820285,
        "Command": "GoroutineReceive",
        "Id": 21,
        "ParentId": 0,
        "From": "",
        "To": "",
        "Channel": "SOgVOX52EN",
        "Value": "9",
        "EventID": "",
        "Duration": 0
    },
    {
        "Time": 783110404,
        "Command": "GoroutineSend",
        "Id": 21,
        "ParentId": 0,
        "From": "",
        "To": "",
        "Channel": "SOgVOX52EN",
        "Value": "10",
        "EventID": "",
        "Duration": 0
    },
    {
        "Time": 783141911,
        "Command": "GoroutineReceive",
        "Id": 20,
        "ParentId": 0,
        "From": "",
        "To": "",
        "Channel": "SOgVOX52EN",
        "Value": "10",
        "EventID": "",
        "Duration": 0
    },
    {
        "Time": 877874936,
        "Command": "GoroutineSend",
        "Id": 20,
        "ParentId": 0,
        "From": "",
        "To": "",
        "Channel": "SOgVOX52EN",
        "Value": "11",
        "EventID": "",
        "Duration": 0
    },
    {
        "Time": 877906316,
        "Command": "GoroutineReceive",
        "Id": 21,
        "ParentId": 0,
        "From": "",
        "To": "",
        "Channel": "SOgVOX52EN",
        "Value": "11",
        "EventID": "",
        "Duration": 0
    },
    {
        "Time": 940003195,
        "Command": "GoroutineSend",
        "Id": 21,
        "ParentId": 0,
        "From": "",
        "To": "",
        "Channel": "SOgVOX52EN",
        "Value": "12",
        "EventID": "",
        "Duration": 0
    },
    {
        "Time": 940038521,
        "Command": "GoroutineReceive",
        "Id": 20,
        "ParentId": 0,
        "From": "",
        "To": "",
        "Channel": "SOgVOX52EN",
        "Value": "12",
        "EventID": "",
        "Duration": 0
    },
    {
        "Time": 1001848759,
        "Command": "GoroutineSend",
        "Id": 20,
        "ParentId": 0,
        "From": "",
        "To": "",
        "Channel": "SOgVOX52EN",
        "Value": "13",
        "EventID": "",
        "Duration": 0
    },
    {
        "Time": 1001898079,
        "Command": "GoroutineReceive",
        "Id": 21,
        "ParentId": 0,
        "From": "",
        "To": "",
        "Channel": "SOgVOX52EN",
        "Value": "13",
        "EventID": "",
        "Duration": 0
    },
    {
        "Time": 1090957792,
        "Command": "GoroutineSend",
        "Id": 21,
        "ParentId": 0,
        "From": "",
        "To": "",
        "Channel": "SOgVOX52EN",
        "Value": "14",
        "EventID": "",
        "Duration": 0
    },
    {
        "Time": 1090990196,
        "Command": "GoroutineReceive",
        "Id": 20,
        "ParentId": 0,
        "From": "",
        "To": "",
        "Channel": "SOgVOX52EN",
        "Value": "14",
        "EventID": "",
        "Duration": 0
    },
    {
        "Time": 1169579123,
        "Command": "GoroutineSend",
        "Id": 20,
        "ParentId": 0,
        "From": "",
        "To": "",
        "Channel": "SOgVOX52EN",
        "Value": "15",
        "EventID": "",
        "Duration": 0
    },
    {
        "Time": 1169613340,
        "Command": "GoroutineReceive",
        "Id": 1,
        "ParentId": 0,
        "From": "",
        "To": "",
        "Channel": "SOgVOX52EN",
        "Value": "15",
        "EventID": "",
        "Duration": 0
    },
    {
        "Time": 1184689502,
        "Command": "GoroutineEnd",
        "Id": 1,
        "ParentId": 0,
        "From": "",
        "To": "",
        "Channel": "",
        "Value": null,
        "EventID": "",
        "Duration": 0
    },
    {
        "Time": 1184689502,
        "Command": "GoroutineEnd",
        "Id": 20,
        "ParentId": 0,
        "From": "",
        "To": "",
        "Channel": "",
        "Value": null,
        "EventID": "",
        "Duration": 0
    },
    {
        "Time": 1184689502,
        "Command": "GoroutineEnd",
        "Id": 21,
        "ParentId": 0,
        "From": "",
        "To": "",
        "Channel": "",
        "Value": null,
        "EventID": "",
        "Duration": 0
    }
]